LoveCourse20162019
